Workbook

Sheet Master Index
A1: IGEN NEWS — MASTER READER LIST (Research Data)
A2: v1.0 — Raw research data for onboarding design: Leaders, Sectors, Industries, Students & Working Professionals
A4: Sheet | B4: Contents | C4: Row Count
A5: Leaders — Full Reader List | B5: All 1,233 leader titles, named individually, grouped by 66 categories — every one is a reader | C5: 1,233
A6: Readers by Sector | B6: 50 sectors, each tagged with which reader types (Leaders/Students/Professionals) apply | C6: 50
A7: Readers by Industry | B7: All 1,350 industries, named individually, mapped to parent sector | C7: 1,350
A8: Students & Professionals — Researched | B8: Researched taxonomy of student degrees/departments + working professionals, organized like the Leader list (Group > Category > Subcategory > Title) | C8: 258

Sheet Leaders - Full Reader List
A1: READER SOURCE 1 — LEADERS (All 1,233 Titles, Named)
A2: Every leader title below is automatically a Reader on IGEN News.
A4: Cat # | B4: Group | C4: Category | D4: Subcategory | E4: Leader Title (= Reader)
A5: 1 | B5: Leadership & Governance | C5: Executive Leadership | D5: Founders | E5: Founder
A6: 1 | B6: Leadership & Governance | C6: Executive Leadership | D6: Founders | E6: Co-Founder
A7: 1 | B7: Leadership & Governance | C7: Executive Leadership | D7: Founders | E7: Founding Partner
A8: 1 | B8: Leadership & Governance | C8: Executive Leadership | D8: Founders | E8: Promoter
A9: 1 | B9: Leadership & Governance | C9: Executive Leadership | D9: Founders | E9: Co-Promoter
A10: 1 | B10: Leadership & Governance | C10: Executive Leadership | D10: Founders | E10: Managing Partner
A11: 1 | B11: Leadership & Governance | C11: Executive Leadership | D11: Board Leadership | E11: Chairman
A12: 1 | B12: Leadership & Governance | C12: Executive Leadership | D12: Board Leadership | E12: Executive Chairman
A13: 1 | B13: Leadership & Governance | C13: Executive Leadership | D13: Board Leadership | E13: Vice Chairman
A14: 1 | B14: Leadership & Governance | C14: Executive Leadership | D14: Board Leadership | E14: Board Director
A15: 1 | B15: Leadership & Governance | C15: Executive Leadership | D15: Board Leadership | E15: Independent Director
A16: 1 | B16: Leadership & Governance | C16: Executive Leadership | D16: Board Leadership | E16: Non-Executive Director
... A1237: 66 | B1237: Supply Chain & Sustainability | C1237: Green Supply Chain | D1237: Supply Chain Sustainability | E1237: Green Supply Chain Analyst
A1238: TOTAL | E1238: =COUNTA(E5:E1237) -> 1233

Sheet Readers by Sector
A1: READER SOURCE 2 — READERS BY SECTOR (50 Sectors)
A2: Which reader type reads which sector's news. Industries under each sector inherit the same reader composition (see 'Readers by Industry').
A4: Sector # | B4: Sector Name | C4: Reader Types That Apply | D4: Industries Under This Sector
A5: 1 | B5: Sector 1 — Agriculture | C5: Leaders (relevant categories) + Students (matching degree field) + Working Professionals (matching department) + General Readers | D5: =COUNTIF('Readers by Industry'!$B:$B,B5) -> 28
A6: 2 | B6: Sector 2 — AI & Cyber Security | C6: Leaders (relevant categories) + Students (matching degree field) + Working Professionals (matching department) + General Readers | D6: =COUNTIF('Readers by Industry'!$B:$B,B6) -> 30
A7: 3 | B7: Sector 3 — Animal Husbandry, Dairying & Fisheries | C7: Leaders (relevant categories) + Students (matching degree field) + Working Professionals (matching department) + General Readers | D7: =COUNTIF('Readers by Industry'!$B:$B,B7) -> 28
A8: 4 | B8: Sector 4 — Atomic Energy | C8: Leaders (relevant categories) + Students (matching degree field) + Working Professionals (matching department) + General Readers | D8: =COUNTIF('Readers by Industry'!$B:$B,B8) -> 27
A9: 5 | B9: Sector 5 — Ayush & Ayurveda & Herbal Medicine | C9: Leaders (relevant categories) + Students (matching degree field) + Working Professionals (matching department) + General Readers | D9: =COUNTIF('Readers by Industry'!$B:$B,B9) -> 31
A10: 6 | B10: Sector 6 — Biotechnology | C10: Leaders (relevant categories) + Students (matching degree field) + Working Professionals (matching department) + General Readers | D10: =COUNTIF('Readers by Industry'!$B:$B,B10) -> 30
A11: 7 | B11: Sector 7 — Chemicals & Fertilizers & Minerals | C11: Leaders (relevant categories) + Students (matching degree field) + Working Professionals (matching department) + General Readers | D11: =COUNTIF('Readers by Industry'!$B:$B,B11) -> 35
A12: 8 | B12: Sector 8 — Petrochemicals | C12: Leaders (relevant categories) + Students (matching degree field) + Working Professionals (matching department) + General Readers | D12: =COUNTIF('Readers by Industry'!$B:$B,B12) -> 27
A13: 9 | B13: Sector 9 — Civil Aviation | C13: Leaders (relevant categories) + Students (matching degree field) + Working Professionals (matching department) + General Readers | D13: =COUNTIF('Readers by Industry'!$B:$B,B13) -> 29
A14: 10 | B14: Sector 10 — Coal | C14: Leaders (relevant categories) + Students (matching degree field) + Working Professionals (matching department) + General Readers | D14: =COUNTIF('Readers by Industry'!$B:$B,B14) -> 25
A15: 11 | B15: Sector 11 — Communications | C15: Leaders (relevant categories) + Students (matching degree field) + Working Professionals (matching department) + General Readers | D15: =COUNTIF('Readers by Industry'!$B:$B,B15) -> 35
A16: 12 | B16: Sector 12 — Consumer Brands | C16: Leaders (relevant categories) + Students (matching degree field) + Working Professionals (matching department) + General Readers | D16: =COUNTIF('Readers by Industry'!$B:$B,B16) -> 30
... A54: 50 | B54: Sector 50 — Waste Management & Circular Economy | C54: Leaders (relevant categories) + Students (matching degree field) + Working Professionals (matching department) + General Readers | D54: =COUNTIF('Readers by Industry'!$B:$B,B54) -> 26

Sheet Readers by Industry
A1: READER SOURCE 3 — READERS BY INDUSTRY (All 1,350 Industries, Named)
A2: Each industry's reader composition = same as its parent Sector (see 'Readers by Sector').
A4: Sector # | B4: Parent Sector | C4: Industry Name | D4: Description
A5: 1 | B5: Sector 1 — Agriculture | C5: Rice Industry | D5: Export of basmati rice, non-basmati rice, parboiled rice, broken rice, organic rice.
A6: 1 | B6: Sector 1 — Agriculture | C6: Wheat & Grain Industry | D6: Wheat, maize, barley, sorghum, millet, bulk grain trading.
A7: 1 | B7: Sector 1 — Agriculture | C7: Dal Processing Industry | D7: Chickpeas, pigeon peas, lentils, mung beans, kidney beans.
A8: 1 | B8: Sector 1 — Agriculture | C8: Spice Industry | D8: Turmeric, cumin, coriander, pepper, cardamom, chili powder, spice blends.
A9: 1 | B9: Sector 1 — Agriculture | C9: Edible Oil Seeds Industry | D9: Sesame seeds, mustard seeds, sunflower seeds, groundnut seeds.
A10: 1 | B10: Sector 1 — Agriculture | C10: Edible Oil Industry | D10: Groundnut oil, mustard oil, sesame oil, sunflower oil, palm oil trading.
A11: 1 | B11: Sector 1 — Agriculture | C11: Fruit Export Industry | D11: Mango, banana, grapes, pomegranate, apple, citrus fruits.
A12: 1 | B12: Sector 1 — Agriculture | C12: Vegetables Export Industry | D12: Onion, potato, tomato, okra, green chili, cabbage.
A13: 1 | B13: Sector 1 — Agriculture | C13: Dry Fruits Industry | D13: Cashew nuts, almonds, pistachios, raisins, walnuts.
A14: 1 | B14: Sector 1 — Agriculture | C14: Coffee Industry | D14: Arabica coffee, Robusta coffee, roasted coffee beans, coffee powder.
A15: 1 | B15: Sector 1 — Agriculture | C15: Tea Industry | D15: Black tea, green tea, specialty tea, organic tea, tea extracts.
A16: 1 | B16: Sector 1 — Agriculture | C16: Cocoa Industry | D16: Cocoa beans, cocoa powder, cocoa butter.
... A1354: 50 | B1354: Sector 50 — Waste Management & Circular Economy | C1354: Extended Producer Responsibility Industry | D1354: EPR compliance, take-back programs, PRO platform services.
A1355: TOTAL | C1355: =COUNTA(C5:C1354) -> 1350

Sheet Students & Professionals
A1: READER SOURCE 4 — STUDENTS & WORKING PROFESSIONALS (Researched)
A2: Researched degree/department taxonomy — Engineering, Medical, Management, Commerce/CA, Law, Sciences, Arts, Journalism, Design, Competitive Exams (UPSC/Police/DRDO/Banking), and Working Professionals by Department.
A4: Group | B4: Category | C4: Subcategory | D4: Reader Title / Degree
A5: Engineering & Technology | B5: Computer Science & IT | C5: Degree Program | D5: Diploma in Computer Engineering
A6: Engineering & Technology | B6: Computer Science & IT | C6: Degree Program | D6: B.Tech/B.E. Computer Science
A7: Engineering & Technology | B7: Computer Science & IT | C7: Degree Program | D7: B.Tech Information Technology
A8: Engineering & Technology | B8: Computer Science & IT | C8: Degree Program | D8: M.Tech/M.E. Computer Science
A9: Engineering & Technology | B9: Computer Science & IT | C9: Degree Program | D9: M.Tech Software Engineering
A10: Engineering & Technology | B10: Computer Science & IT | C10: Degree Program | D10: PhD Computer Science
A11: Engineering & Technology | B11: Electronics & Communication | C11: Degree Program | D11: Diploma in Electronics
A12: Engineering & Technology | B12: Electronics & Communication | C12: Degree Program | D12: B.Tech Electronics & Communication (ECE)
A13: Engineering & Technology | B13: Electronics & Communication | C13: Degree Program | D13: B.Tech VLSI Design
A14: Engineering & Technology | B14: Electronics & Communication | C14: Degree Program | D14: M.Tech Electronics & Communication
A15: Engineering & Technology | B15: Electronics & Communication | C15: Degree Program | D15: PhD Electronics Engineering
... A262: Working Professionals (by Department) | B262: Innovation Ecosystem, Partnerships & Alliances | C262: Early/Mid-Career Title | D262: Alliances Executive
A263: TOTAL | D263: =COUNTA(D5:D262) -> 258
